fetch/instruction_memory.v
module instructions_memory(
    input [10:0] address, //saida da ula
    output [31:0] read_data // read data
);
   reg [31:0] Memory [2047:0];

   initial begin
    /*
    Data Memory -> Valores que serão adicionados no banco de registradores
    */
    // lw x6, 0(x0)
    //Estrutura da instrução de load = {imm[11:0], rs1, 010, rd, 0000011}
     Memory[0] = 32'b000000000000_00000_010_00110_0000011; 

    // sd x6, 64(x0)
    //Estrutura da instrução = {offset[11:5], rs2, rs1, 010, offset[4:0], 0100011}
     Memory[1] = 32'b0000010_00000_00000_010_00000_0100011;
     Memory[2] = 32'd3;
     Memory[3] = 32'd4;
     Memory[4] = 32'd5;
     Memory[5] = 32'd6;
     Memory[6] = 32'd7;
     Memory[20] = 32'd20;
     Memory[21] = 32'd21;
     Memory[22] = 32'd22;
     Memory[23] = 32'd23;
     Memory[24] = 32'd24;
     Memory[25] = 32'd25;
     Memory[26] = 32'd26;
     Memory[27] = 32'd27;
     Memory[28] = 32'd28;
   end

   assign read_data = Memory[address];  
endmodule

fetch/flopenr.v
module flopenr #(parameter WIDTH = 8) (
    input clk, reset, en,
    input [WIDTH-1:0] d,
    output reg [WIDTH-1:0] q
);
always @(posedge clk or posedge reset) begin
    if (reset) 
        q <= 0;
    else if (en) 
        q <= d;
end

endmodule

fetch/mux2.v
module mux2 #(parameter WIDTH = 8) (
    input [WIDTH-1:0] d0, d1,
    input s,
    output [WIDTH-1:0] y
);
assign y = s ? d1 : d0;  //se s = 1, y = d1
                         //se s = 0, y = d0
  
endmodule

fetch/fetch.v
module fetch (
    input clock,
    input reset_pc,

    //Input UC
    input PCSrcE,

    //Input Hazard
    input StallF,
    
    //Input Execute
    input [63:0] pc_target,

    //Outputs

    output [31:0] InstrF,        //RD do Instruction Memory
    output [63:0] PCF,           //Saída do Reg
    output [63:0] PCPlus4F    

);
    wire [63:0] s_PCF_Linha;     //Saída do Mux
    wire [63:0] s_PCPlus4F;
    wire [63:0] s_PCF;
    
    // MUX para selecionar o próximo valor do PC com base em PCSrcE

    mux2 #(
        .WIDTH(64)
    ) PCinstruc (
        .d0(s_PCPlus4F),
        .d1(pc_target),
        .s(PCSrcE),
        .y(s_PCF_Linha)
    );

    // Flip-flop com enable e reset para o contador do programa
    flopenr #(
            .WIDTH(64)
        ) 
        pcreg
        (
            .clk(clock), 
            .reset(reset_pc), 
            .en(~StallF), 
            .d(s_PCF_Linha), 
            .q(s_PCF)
        );

    // Instância da memória de instruções
    instructions_memory inst_mem (
        .address(s_PCF[10:0]),
        .read_data(InstrF)
    );

    //Somador
    assign s_PCPlus4F = s_PCF + 64'd1;

    assign PCF = s_PCF;
    assign PCPlus4F = s_PCPlus4F;

endmodule

fetch/fetch_tb.v

//Comandos Wind:

//iverilog -o wave.vvp fetch_tb.v fetch.v flopenr.v instruction_memory.v mux2.v

//vvp wave.vvp

//gtkwave wave.vcd


//Linux: make

`timescale 1ns / 1ps
module fetch_tb;

    // Sinais de entrada do DUT
    reg clock;
    reg reset_pc;
    reg PCSrcE;
    reg StallF;
    reg [63:0] pc_target;

    // Sinais de saída do DUT
    wire [31:0] InstrF;
    wire [63:0] PCF;
    wire [63:0] PCPlus4F;

    // Instanciando o DUT (Device Under Test)
    fetch uut (
        .clock(clock),
        .reset_pc(reset_pc),
        .PCSrcE(PCSrcE),
        .StallF(StallF),
        .pc_target(pc_target),
        .InstrF(InstrF),
        .PCF(PCF),
        .PCPlus4F(PCPlus4F)
    );

    // Geração de clock
    initial begin
        $dumpfile("wave.vcd");
        $dumpvars(0, fetch_tb);
        clock = 0;
        forever #5 clock = ~clock; // Clock de 10 unidades de tempo
    end

    // Estímulos
    initial begin
        // Inicializa os sinais
        reset_pc = 1;
        PCSrcE = 0;
        StallF = 0;
        pc_target = 64'd0;

        // Espera alguns ciclos para o reset
        #10;
        reset_pc = 0;

        // Teste 1: Incremento normal do PC
        #10;
        StallF = 0;    // Sem stall
        PCSrcE = 0;    // PC continua incrementando normalmente

        // Teste 2: Muda o PC com PCSrcE
        #20;
        PCSrcE = 1;    // Altera o PC para pc_target
        pc_target = 64'd20;

        #20
        PCSrcE = 0;

        // Teste 3: Sinal de stall
        #30;
        StallF = 1;    // Mantém o valor atual do PC

        #30
        StallF = 0;

        // Teste 4: Reseta o PC
        #40;
        reset_pc = 1;

        // Fim da simulação
        #50;
        $finish;
    end

    // Monitor para observar os sinais
    initial begin
        $monitor(
            "Time=%0t | reset_pc=%b | PCSrcE=%b | StallF=%b | pc_target=%d | PCF=%d | PCPlus4F=%d | InstrF=%h",
            $time, reset_pc, PCSrcE, StallF, pc_target, PCF, PCPlus4F, InstrF
        );
    end

endmodule

fetch/wave.vcd
$date
	Sun Nov 17 13:00:01 2024
$end
$version
	Icarus Verilog
$end
$timescale
	1ps
$end
$scope module fetch_tb $end
$var wire 64 ! PCPlus4F [63:0] $end
$var wire 64 " PCF [63:0] $end
$var wire 32 # InstrF [31:0] $end
$var reg 1 $ PCSrcE $end
$var reg 1 % StallF $end
$var reg 1 & clock $end
$var reg 64 ' pc_target [63:0] $end
$var reg 1 ( reset_pc $end
$scope module uut $end
$var wire 64 ) PCF [63:0] $end
$var wire 64 * PCPlus4F [63:0] $end
$var wire 1 $ PCSrcE $end
$var wire 1 % StallF $end
$var wire 1 & clock $end
$var wire 64 + pc_target [63:0] $end
$var wire 1 ( reset_pc $end
$var wire 64 , s_PCPlus4F [63:0] $end
$var wire 64 - s_PCF_Linha [63:0] $end
$var wire 64 . s_PCF [63:0] $end
$var wire 32 / InstrF [31:0] $end
$scope module PCinstruc $end
$var wire 64 0 d0 [63:0] $end
$var wire 64 1 d1 [63:0] $end
$var wire 1 $ s $end
$var wire 64 2 y [63:0] $end
$upscope $end
$scope module inst_mem $end
$var wire 11 3 address [10:0] $end
$var wire 32 4 read_data [31:0] $end
$upscope $end
$scope module pcreg $end
$var wire 1 & clk $end
$var wire 64 5 d [63:0] $end
$var wire 1 6 en $end
$var wire 1 ( reset $end
$var reg 64 7 q [63:0] $end
$upscope $end
$upscope $end
$upscope $end
$enddefinitions $end
#0
$dumpvars
b0 7
16
b1 5
b10001100000011 4
b0 3
b1 2
b0 1
b1 0
b10001100000011 /
b0 .
b1 -
b1 ,
b0 +
b1 *
b0 )
1(
b0 '
0&
0%
0$
b10001100000011 #
b0 "
b1 !
$end
#5000
1&
#10000
0&
0(
#15000
b10 -
b10 2
b10 5
b100000000000010000000100011 #
b100000000000010000000100011 /
b100000000000010000000100011 4
b1 3
b10 !
b10 *
b10 ,
b10 0
b1 "
b1 )
b1 .
b1 7
1&
#20000
0&
#25000
b11 -
b11 2
b11 5
b11 #
b11 /
b11 4
b10 3
b11 !
b11 *
b11 ,
b11 0
b10 "
b10 )
b10 .
b10 7
1&
#30000
0&
#35000
b100 -
b100 2
b100 5
b100 #
b100 /
b100 4
b11 3
b100 !
b100 *
b100 ,
b100 0
b11 "
b11 )
b11 .
b11 7
1&
#40000
b10100 -
b10100 2
b10100 5
0&
b10100 '
b10100 +
b10100 1
1$
#45000
b10100 #
b10100 /
b10100 4
b10100 3
b10101 !
b10101 *
b10101 ,
b10101 0
b10100 "
b10100 )
b10100 .
b10100 7
1&
#50000
0&
#55000
1&
#60000
b10101 -
b10101 2
b10101 5
0&
0$
#65000
b10110 -
b10110 2
b10110 5
b10101 #
b10101 /
b10101 4
b10101 3
b10110 !
b10110 *
b10110 ,
b10110 0
b10101 "
b10101 )
b10101 .
b10101 7
1&
#70000
0&
#75000
b10111 -
b10111 2
b10111 5
b10110 #
b10110 /
b10110 4
b10110 3
b10111 !
b10111 *
b10111 ,
b10111 0
b10110 "
b10110 )
b10110 .
b10110 7
1&
#80000
0&
#85000
b11000 -
b11000 2
b11000 5
b10111 #
b10111 /
b10111 4
b10111 3
b11000 !
b11000 *
b11000 ,
b11000 0
b10111 "
b10111 )
b10111 .
b10111 7
1&
#90000
06
0&
1%
#95000
1&
#100000
0&
#105000
1&
#110000
0&
#115000
1&
#120000
16
0&
0%
#125000
b11001 -
b11001 2
b11001 5
b11000 #
b11000 /
b11000 4
b11000 3
b11001 !
b11001 *
b11001 ,
b11001 0
b11000 "
b11000 )
b11000 .
b11000 7
1&
#130000
0&
#135000
b11010 -
b11010 2
b11010 5
b11001 #
b11001 /
b11001 4
b11001 3
b11010 !
b11010 *
b11010 ,
b11010 0
b11001 "
b11001 )
b11001 .
b11001 7
1&
#140000
0&
#145000
b11011 -
b11011 2
b11011 5
b11010 #
b11010 /
b11010 4
b11010 3
b11011 !
b11011 *
b11011 ,
b11011 0
b11010 "
b11010 )
b11010 .
b11010 7
1&
#150000
0&
#155000
b11100 -
b11100 2
b11100 5
b11011 #
b11011 /
b11011 4
b11011 3
b11100 !
b11100 *
b11100 ,
b11100 0
b11011 "
b11011 )
b11011 .
b11011 7
1&
#160000
b1 -
b1 2
b1 5
b10001100000011 #
b10001100000011 /
b10001100000011 4
b0 3
b1 !
b1 *
b1 ,
b1 0
b0 "
b0 )
b0 .
b0 7
0&
1(
