memory/data_memory.v
module data_memory(input clk,      
              //input mem_read, (????)
              input mem_write,
              input [63:0] endereco, // Endereço de saída da ULA
              input [63:0] write_data, // Dados a serem escritos
              output [63:0] read_data // Dados a serem lidos
             );
   reg [63:0] endereco_atual;
   reg [7:0] Memory [2047:0];

   /*
    Memoria 64x32
    Neste caso, foi instanciado em bytes, por isso são 2048 posições
   */
   initial begin
     /*
      Initial Data Memory -> Set up expected initial values
     */
     // Initial value at address 0 (for test case 1)
     Memory[0] = 8'd0;
     Memory[1] = 8'd0;
     Memory[2] = 8'd0;
     Memory[3] = 8'd0;
     Memory[4] = 8'd0;
     Memory[5] = 8'd0;
     Memory[6] = 8'd0;
     Memory[7] = 8'd8; // Initial value of 64'd8 at address 0

     // Values at address 10 and 20 will be set during the test cases
     // but initialized here to a known state:
     Memory[8] = 8'd0;
     Memory[9] = 8'd0;
     Memory[10] = 8'd0;
     Memory[11] = 8'd0;
     Memory[12] = 8'd0;
     Memory[13] = 8'd0;
     Memory[14] = 8'd0;
     Memory[15] = 8'd7; // Initial value at address 7

     Memory[16] = 8'd0;
     Memory[17] = 8'd0;
     Memory[18] = 8'd0;
     Memory[19] = 8'd0;
     Memory[20] = 8'd0;
     Memory[21] = 8'd0;
     Memory[22] = 8'd0;
     Memory[23] = 8'd0; // Initial value at address 20
   end
   
   // Concatenate bytes to form 64-bit read data
   assign read_data = {Memory[endereco + 0], Memory[endereco + 1], 
                       Memory[endereco + 2], Memory[endereco + 3],
                       Memory[endereco + 4], Memory[endereco + 5], 
                       Memory[endereco + 6], Memory[endereco + 7]}; 

   // Write data on positive clock edge if mem_write is high
   always @(posedge clk) begin        
        if (mem_write == 1) begin
          Memory[endereco + 7] <= write_data[7:0];
          Memory[endereco + 6] <= write_data[15:8];
          Memory[endereco + 5] <= write_data[23:16];
          Memory[endereco + 4] <= write_data[31:24];
          Memory[endereco + 3] <= write_data[39:32];
          Memory[endereco + 2] <= write_data[47:40];
          Memory[endereco + 1] <= write_data[55:48];
          Memory[endereco] <= write_data[63:56];
        end
   end      
endmodule

cu/flopr.v
module flopr #(parameter WIDTH = 8) (
    input clk, reset,
    input [WIDTH-1:0] d,
    output reg [WIDTH-1:0] q
);
always @(posedge clk or posedge reset) begin
    if (reset) 
        q <= 0;
    else 
        q <= d;
end

endmodule

memory/memory.v

module memory (
    input clock,
    input reset,
    input [63:0] ALUResultE,              //ALUResultE
    input [63:0] WriteDataE,              //WriteDataE
    input [4:0]  RdE,                       //RdE
    input [63:0] PCPlus4E,        //PCPlus4E
    input MemWriteM,                       //Vem da UC
    //input [1:0] result_src_m,
    
    output [4:0]  RdM,
    output [63:0] PCPlus4M,
    output [63:0] RD_Memory,
    output [63:0] ALUResultM
);

    wire [63:0] WriteDataM;


    flopr #(
            .WIDTH(197) 
        ) regM (
            .clk(clock), 
            .reset(reset),
            .d({ALUResultE, WriteDataE, RdE, PCPlus4E}),
            .q({ALUResultM, WriteDataM, RdM, PCPlus4M})
    );

    data_memory data_mem (
        .clk(clock),
        //.mem_read(1'b1),         // ?????
        .mem_write(MemWriteM),  //Write Enable//
        .endereco(ALUResultM),   //A //
        .write_data(WriteDataM), //WD //
        .read_data(RD_Memory)    //RD do Data Memory
    );


endmodule

memory/memory_tb.v
// //iverilog -o wave.vvp data_memory.v memory_tb.v memory.v flopr.v

// vvp wave.vvp

// gtkwave wave.vcd

//Linux: make

`timescale 1ns / 1ps

module memory_tb;

    reg clock;
    reg reset;
    reg [63:0] ALUResultE;
    reg [63:0] WriteDataE;
    reg [4:0] RdE;
    reg [63:0] PCPlus4E;
    reg MemWriteM;

    wire [4:0] RdM;
    wire [63:0] PCPlus4M;
    wire [63:0] RD_Memory;
    wire [63:0] ALUResultM;

    // Instancia o módulo memory
    memory uut (
        .clock(clock),
        .reset(reset),
        .ALUResultE(ALUResultE),
        .WriteDataE(WriteDataE),
        .RdE(RdE),
        .PCPlus4E(PCPlus4E),
        .MemWriteM(MemWriteM),
        .RdM(RdM),
        .PCPlus4M(PCPlus4M),
        .RD_Memory(RD_Memory),
        .ALUResultM(ALUResultM)
    );

    // Gera clock
    always #5 clock = ~clock;

    initial begin
        $dumpfile("wave.vcd");
        $dumpvars(0, memory_tb);
        // Inicialização
        clock = 0;
        reset = 1;
        ALUResultE = 0;
        WriteDataE = 0;
        RdE = 0;
        PCPlus4E = 0;
        MemWriteM = 0;

        // Solta o reset
        #10 reset = 0;

        // Teste de escrita na memória
        #10 ALUResultE = 64'h000000000000000A;  // Endereço
        WriteDataE = 64'hDEADBEEFDEADBEEF;     // Dado para escrever
        RdE = 5'b00001;
        PCPlus4E = 64'h0000000000000004;
        MemWriteM = 1;                         // Habilita escrita na memória

        #20 MemWriteM = 0;                     // Desabilita escrita

        // Teste de leitura da memória
        #10 ALUResultE = 64'h000000000000000A; // Endereço já escrito
        WriteDataE = 64'h0;
        RdE = 5'b00010;

        // Aguarda alguns ciclos e verifica resultados
        #30;
        $display("ALUResultM: %h", ALUResultM);
        $display("PCPlus4M: %h", PCPlus4M);
        $display("RD_Memory: %h", RD_Memory);

        // Finaliza simulação
        #50 $finish;
    end

endmodule

memory/wave.vcd
$date
	Sun Nov 17 16:39:34 2024
$end
$version
	Icarus Verilog
$end
$timescale
	1ps
$end
$scope module memory_tb $end
$var wire 5 ! RdM [4:0] $end
$var wire 64 " RD_Memory [63:0] $end
$var wire 64 # PCPlus4M [63:0] $end
$var wire 64 $ ALUResultM [63:0] $end
$var reg 64 % ALUResultE [63:0] $end
$var reg 1 & MemWriteM $end
$var reg 64 ' PCPlus4E [63:0] $end
$var reg 5 ( RdE [4:0] $end
$var reg 64 ) WriteDataE [63:0] $end
$var reg 1 * clock $end
$var reg 1 + reset $end
$scope module uut $end
$var wire 64 , ALUResultE [63:0] $end
$var wire 1 & MemWriteM $end
$var wire 64 - PCPlus4E [63:0] $end
$var wire 5 . RdE [4:0] $end
$var wire 64 / WriteDataE [63:0] $end
$var wire 1 * clock $end
$var wire 1 + reset $end
$var wire 64 0 WriteDataM [63:0] $end
$var wire 5 1 RdM [4:0] $end
$var wire 64 2 RD_Memory [63:0] $end
$var wire 64 3 PCPlus4M [63:0] $end
$var wire 64 4 ALUResultM [63:0] $end
$scope module data_mem $end
$var wire 1 * clk $end
$var wire 64 5 endereco [63:0] $end
$var wire 1 & mem_write $end
$var wire 64 6 write_data [63:0] $end
$var wire 64 7 read_data [63:0] $end
$upscope $end
$scope module regM $end
$var wire 1 * clk $end
$var wire 197 8 d [196:0] $end
$var wire 1 + reset $end
$var reg 197 9 q [196:0] $end
$upscope $end
$upscope $end
$upscope $end
$enddefinitions $end
#0
$dumpvars
b0 9
b0 8
b1000 7
b0 6
b0 5
b0 4
b0 3
b1000 2
b0 1
b0 0
b0 /
b0 .
b0 -
b0 ,
1+
0*
b0 )
b0 (
b0 '
0&
b0 %
b0 $
b0 #
b1000 "
b0 !
$end
#5000
1*
#10000
0*
0+
#15000
1*
#20000
0*
1&
b100 '
b100 -
b1 (
b1 .
b1101111010101101101111101110111111011110101011011011111011101111 )
b1101111010101101101111101110111111011110101011011011111011101111 /
b10101101111010101101101111101110111111011110101011011011111011101111000010000000000000000000000000000000000000000000000000000000000000100 8
b1010 %
b1010 ,
#25000
b100 #
b100 3
b1 !
b1 1
b1101111010101101101111101110111111011110101011011011111011101111 0
b1101111010101101101111101110111111011110101011011011111011101111 6
b1010 $
b1010 4
b1010 5
b1110000000000000000 "
b1110000000000000000 2
b1110000000000000000 7
b10101101111010101101101111101110111111011110101011011011111011101111000010000000000000000000000000000000000000000000000000000000000000100 9
1*
#30000
0*
#35000
b1101111010101101101111101110111111011110101011011011111011101111 "
b1101111010101101101111101110111111011110101011011011111011101111 2
b1101111010101101101111101110111111011110101011011011111011101111 7
1*
#40000
0*
0&
#45000
1*
#50000
0*
b10 (
b10 .
b10100000000000000000000000000000000000000000000000000000000000000000000100000000000000000000000000000000000000000000000000000000000000100 8
b0 )
b0 /
#55000
b10 !
b10 1
b0 0
b0 6
b10100000000000000000000000000000000000000000000000000000000000000000000100000000000000000000000000000000000000000000000000000000000000100 9
1*
