execute/ULA.v
module ULA(
    input [63:0] SrcA,         // Entrada de 64 bits
    input [63:0] SrcB,         // Entrada de 64 bits
    input [2:0] ALUControl,    // Controle da operação (3 bits)
    output reg [63:0] ALUResult, // Resultado da operação (64 bits)
    output ZeroE               // Sinal de igualdade (1 bit)
);

    // Calcula o sinal de igualdade para subtração
    assign ZeroE = (ALUControl == 3'b001 && (SrcA - SrcB) == 64'b0) ? 1'b1 : 1'b0;

    always @(*) begin
        case (ALUControl)
            3'b000: ALUResult = SrcA + SrcB;                      // ADD
            3'b001: ALUResult = SrcA - SrcB;                      // SUBTRACT
            3'b101: ALUResult = (SrcA < SrcB) ? 64'b1 : 64'b0;    // SET LESS THAN
            3'b011: ALUResult = SrcA | SrcB;                      // OR
            3'b010: ALUResult = SrcA & SrcB;                      // AND
            default: ALUResult = 64'b0;                           // Valor padrão
        endcase
    end

endmodule

fetch/mux2.v
module mux2 #(parameter WIDTH = 8) (
    input [WIDTH-1:0] d0, d1,
    input s,
    output [WIDTH-1:0] y
);
assign y = s ? d1 : d0;  //se s = 1, y = d1
                         //se s = 0, y = d0
  
endmodule

write_back/mux3.v
module mux3 #(parameter WIDTH = 8) (
    input [WIDTH-1:0] d0, d1, d2,
    input [1:0] s,
    output reg [WIDTH-1:0] y
);
always @(*) begin
    if (s[1])      //s = 10 ou 11
        y = d2;
    else if (s[0]) //s = 01
        y = d1;
    else           //s = 00
        y = d0;
end

endmodule

execute/floprc.v
module floprc #(parameter WIDTH = 8) (
    input clk,
    input reset,
    input clear,
    input [WIDTH-1:0] d,
    output reg [WIDTH-1:0] q
);
always @(posedge clk or posedge reset) begin
    if (reset) 
        q <= 0;
    else if (clear) 
        q <= 0;
    else 
        q <= d;
end

endmodule

execute/execute.v
module execute (
    input clock,
    input reset,

    /* inputs da UC */
    //input reg_write_d,
    //input [1:0] result_src_d,
    //input mem_write_d,
    //input jump,
    //input branch,
    input [2:0] ALUControlE,
    input ALUSrcE,

    // input da saída do pipeline de Memory
    input [63:0] ALUResultM,

    //input da saída do MUX de WriteBack

    input [63:0] ResultW,

    // inputs da Unidade Hazard
    input FlushE,
    input [1:0] ForwardAE,
    input [1:0] ForwardBE,

    /* inputs do decode */
    input [63:0] read_data1,                  //RD1
    input [63:0] read_data2,                  //RD2
    input [63:0] PCD,                         //PCD
    input [4:0]  RdD,                         //RdD
    input [63:0] ImmExtD,                     //ImmExtD
    input [63:0] PCPlus4D,                    //PCPlus4D
    input [4:0]  Rs1D,                        //Rs1D
    input [4:0]  Rs2D,                        //Rs2D

    /* outputs */           
    output zeroE,
    output [63:0] PCTargetE,                  //PCTargetE
    
    output [63:0] ALUResultE,
    output [63:0] WriteDataE,
    output [4:0]  RdE,
    output [63:0] PCPlus4E              //PCPlus4E
);

    wire [63:0] src_b;
    wire and_out;


    //Saída do Registrador Execute Pipeline
    wire [63:0] RD1E;
    wire [63:0] RD2E;
    wire [63:0] PCE;
    wire [4:0]  Rs1E;
    wire [4:0]  Rs2E;
    wire [63:0] ImmExtE;



    wire [63:0] SrcAE_wire;         //Saída do MUX do ForwardAE


    floprc #(
        .WIDTH(335)
    ) regE (
        .clk(clock),
        .reset(reset),
        .clear(FlushE),        
        .d({read_data1,read_data2,PCD,Rs1D,
            Rs2D,RdD,ImmExtD,PCPlus4D}),

        .q({RD1E, RD2E, PCE, Rs1E, Rs2E, RdE, ImmExtE, PCPlus4E})
    );


    // Mux do forwardAE

    mux3 #(
        .WIDTH(64)
    ) faemux (
        .d0(RD1E), 
        .d1(ResultW), 
        .d2(ALUResultM), 
        .s(ForwardAE), 
        .y(SrcAE_wire)
    );

    mux3 #(
        .WIDTH(64)
    ) fbemux (
        .d0(RD2E),
        .d1(ResultW),
        .d2(ALUResultM),
        .s(ForwardBE), 
        .y(WriteDataE)
    );

    mux2 #(
        .WIDTH(64)
    ) srcbmux (
        .d0(WriteDataE),
        .d1(ImmExtE),
        .s(ALUSrcE),
        .y(src_b)
    );

    // ALU ALU (
    //     .A(SrcAE_wire), 
    //     .B(src_b), 
    //     .ALUOp(ALUControlE), 
    //     .result(ALUResultE), 
    //     .equal(zeroE), 
    //     .not_equal(), 
    //     .lesser_than(), 
    //     .greater_or_equal(), 
    //     .unsigned_lesser(), 
    //     .unsigned_greater_equal()
    // );

    ULA ULA(
        .SrcA(SrcAE_wire),
        .SrcB(src_b),
        .ALUControl(ALUControlE),
        .ALUResult(ALUResultE),
        .ZeroE(zeroE)
    );


    //O PC Source não é necessário aqui, a UC já foi feita para receber a flag ZERO_E.
    //Ela quem vai decidir de a próxima instrução será PCTarget ou PCPlus4

    //and (and_out, zero, branch);    //or (pc_source, and_out, jum                     p);


    assign PCTargetE = PCE  + ImmExtD;          

    //assign zero = ALUResultE == 64'b0;


endmodule

execute/execute_tb.v
`timescale 1ns / 1ps

module execute_tb;

    // Declaração de sinais
    reg clock;
    reg reset;
    reg [2:0] ALUControlE;
    reg ALUSrcE;
    reg [63:0] ALUResultM;
    reg [63:0] ResultW;
    reg FlushE;
    reg [1:0] ForwardAE;
    reg [1:0] ForwardBE;
    reg [63:0] read_data1;
    reg [63:0] read_data2;
    reg [63:0] PCD;
    reg [4:0] RdD;
    reg [63:0] ImmExtD;
    reg [63:0] PCPlus4D;
    reg [4:0] Rs1D;
    reg [4:0] Rs2D;

    // Saídas
    wire zeroE;
    wire [63:0] PCTargetE;
    wire [63:0] ALUResultE;
    wire [63:0] WriteDataE;
    wire [4:0] RdE;
    wire [63:0] PCPlus4E;

    // Instanciando o módulo execute
    execute uut (
        .clock(clock),
        .reset(reset),
        .ALUControlE(ALUControlE),
        .ALUSrcE(ALUSrcE),
        .ALUResultM(ALUResultM),
        .ResultW(ResultW),
        .FlushE(FlushE),
        .ForwardAE(ForwardAE),
        .ForwardBE(ForwardBE),
        .read_data1(read_data1),
        .read_data2(read_data2),
        .PCD(PCD),
        .RdD(RdD),
        .ImmExtD(ImmExtD),
        .PCPlus4D(PCPlus4D),
        .Rs1D(Rs1D),
        .Rs2D(Rs2D),
        .zeroE(zeroE),
        .PCTargetE(PCTargetE),
        .ALUResultE(ALUResultE),
        .WriteDataE(WriteDataE),
        .RdE(RdE),
        .PCPlus4E(PCPlus4E)
    );

    // Geração do clock
    always begin
        #5 clock = ~clock; // Toggle a cada 5 unidades de tempo
    end

    // Inicializando sinais e aplicando estímulos
    initial begin
        // Inicialização
        clock = 0;
        reset = 0;
        ALUControlE = 4'b0000;
        ALUSrcE = 0;
        ALUResultM = 64'b0;
        ResultW = 64'b0;
        FlushE = 0;
        ForwardAE = 2'b00;
        ForwardBE = 2'b00;
        read_data1 = 64'hA5A5A5A5A5A5A5A5;
        read_data2 = 64'h5A5A5A5A5A5A5A5A;
        PCD = 64'h0000000000001000;
        RdD = 5'b00001;
        ImmExtD = 64'h0000000000000010;
        PCPlus4D = 64'h0000000000001004;
        Rs1D = 5'b00001;
        Rs2D = 5'b00010;

        // Reset
        reset = 1;
        #10 reset = 0;

        // Teste 1: ALUControlE = 0000, ALUSrcE = 0 (Read data2)
        ALUControlE = 4'b0000;
        ALUSrcE = 0;
        ForwardAE = 2'b00; // Sem forward
        ForwardBE = 2'b00; // Sem forward
        #10;

        // Teste 2: ALUControlE = 0001, ALUSrcE = 1 (Immediate)
        ALUControlE = 4'b0001;
        ALUSrcE = 1;
        #10;

        // Teste 3: Forwarding de ResultW
        ForwardAE = 2'b01; // Forward de ResultW para RS1
        ForwardBE = 2'b01; // Forward de ResultW para RS2
        ResultW = 64'hDEADBEEFDEADBEEF;
        #10;

        // Teste 4: FlushE ativo
        FlushE = 1;
        #10;
        FlushE = 0;

        // Teste 5: ALUResultM como entrada para ForwardAE
        ALUResultM = 64'h123456789ABCDEF0;
        ForwardAE = 2'b10; // Forward de ALUResultM para RS1
        #10;

        // Teste 6: Operação ALU com diferentes ALUControlE
        ALUControlE = 4'b0010; // Soma
        #10;
        ALUControlE = 4'b0110; // Subtração
        #10;

        // Finalizando o teste
        $finish;
    end

    // Monitoramento das saídas
    initial begin
        $dumpfile("wave.vcd");
        $dumpvars(0, execute_tb);
        $monitor("Time: %0t | ALUResultE: %h | WriteDataE: %h | PCTargetE: %h | ZeroE: %b",
                 $time, ALUResultE, WriteDataE, PCTargetE, zeroE);
    end

endmodule

execute/wave.vcd
$date
	Sun Nov 17 15:57:55 2024
$end
$version
	Icarus Verilog
$end
$timescale
	1ps
$end
$scope module execute_tb $end
$var wire 1 ! zeroE $end
$var wire 64 " WriteDataE [63:0] $end
$var wire 5 # RdE [4:0] $end
$var wire 64 $ PCTargetE [63:0] $end
$var wire 64 % PCPlus4E [63:0] $end
$var wire 64 & ALUResultE [63:0] $end
$var reg 3 ' ALUControlE [2:0] $end
$var reg 64 ( ALUResultM [63:0] $end
$var reg 1 ) ALUSrcE $end
$var reg 1 * FlushE $end
$var reg 2 + ForwardAE [1:0] $end
$var reg 2 , ForwardBE [1:0] $end
$var reg 64 - ImmExtD [63:0] $end
$var reg 64 . PCD [63:0] $end
$var reg 64 / PCPlus4D [63:0] $end
$var reg 5 0 RdD [4:0] $end
$var reg 64 1 ResultW [63:0] $end
$var reg 5 2 Rs1D [4:0] $end
$var reg 5 3 Rs2D [4:0] $end
$var reg 1 4 clock $end
$var reg 64 5 read_data1 [63:0] $end
$var reg 64 6 read_data2 [63:0] $end
$var reg 1 7 reset $end
$scope module uut $end
$var wire 3 8 ALUControlE [2:0] $end
$var wire 64 9 ALUResultM [63:0] $end
$var wire 1 ) ALUSrcE $end
$var wire 1 * FlushE $end
$var wire 2 : ForwardAE [1:0] $end
$var wire 2 ; ForwardBE [1:0] $end
$var wire 64 < ImmExtD [63:0] $end
$var wire 64 = PCD [63:0] $end
$var wire 64 > PCPlus4D [63:0] $end
$var wire 5 ? RdD [4:0] $end
$var wire 64 @ ResultW [63:0] $end
$var wire 5 A Rs1D [4:0] $end
$var wire 5 B Rs2D [4:0] $end
$var wire 1 4 clock $end
$var wire 64 C read_data1 [63:0] $end
$var wire 64 D read_data2 [63:0] $end
$var wire 1 7 reset $end
$var wire 1 ! zeroE $end
$var wire 64 E src_b [63:0] $end
$var wire 64 F WriteDataE [63:0] $end
$var wire 64 G SrcAE_wire [63:0] $end
$var wire 5 H Rs2E [4:0] $end
$var wire 5 I Rs1E [4:0] $end
$var wire 5 J RdE [4:0] $end
$var wire 64 K RD2E [63:0] $end
$var wire 64 L RD1E [63:0] $end
$var wire 64 M PCTargetE [63:0] $end
$var wire 64 N PCPlus4E [63:0] $end
$var wire 64 O PCE [63:0] $end
$var wire 64 P ImmExtE [63:0] $end
$var wire 64 Q ALUResultE [63:0] $end
$scope module ULA $end
$var wire 3 R ALUControl [2:0] $end
$var wire 1 ! ZeroE $end
$var wire 64 S SrcB [63:0] $end
$var wire 64 T SrcA [63:0] $end
$var reg 64 U ALUResult [63:0] $end
$upscope $end
$scope module faemux $end
$var wire 64 V d0 [63:0] $end
$var wire 64 W d1 [63:0] $end
$var wire 64 X d2 [63:0] $end
$var wire 2 Y s [1:0] $end
$var reg 64 Z y [63:0] $end
$upscope $end
$scope module fbemux $end
$var wire 64 [ d0 [63:0] $end
$var wire 64 \ d1 [63:0] $end
$var wire 64 ] d2 [63:0] $end
$var wire 2 ^ s [1:0] $end
$var reg 64 _ y [63:0] $end
$upscope $end
$scope module regE $end
$var wire 1 * clear $end
$var wire 1 4 clk $end
$var wire 335 ` d [334:0] $end
$var wire 1 7 reset $end
$var reg 335 a q [334:0] $end
$upscope $end
$scope module srcbmux $end
$var wire 64 b d0 [63:0] $end
$var wire 64 c d1 [63:0] $end
$var wire 1 ) s $end
$var wire 64 d y [63:0] $end
$upscope $end
$upscope $end
$upscope $end
$enddefinitions $end
#0
$dumpvars
b0 d
b0 c
b0 b
b0 a
b10100101101001011010010110100101101001011010010110100101101001010101101001011010010110100101101001011010010110100101101001011010000000000000000000000000000000000000000000000000000100000000000000001000100000100000000000000000000000000000000000000000000000000000000000100000000000000000000000000000000000000000000000000000001000000000100 `
b0 _
b0 ^
b0 ]
b0 \
b0 [
b0 Z
b0 Y
b0 X
b0 W
b0 V
b0 U
b0 T
b0 S
b0 R
b0 Q
b0 P
b0 O
b0 N
b10000 M
b0 L
b0 K
b0 J
b0 I
b0 H
b0 G
b0 F
b0 E
b101101001011010010110100101101001011010010110100101101001011010 D
b1010010110100101101001011010010110100101101001011010010110100101 C
b10 B
b1 A
b0 @
b1 ?
b1000000000100 >
b1000000000000 =
b10000 <
b0 ;
b0 :
b0 9
b0 8
17
b101101001011010010110100101101001011010010110100101101001011010 6
b1010010110100101101001011010010110100101101001011010010110100101 5
04
b10 3
b1 2
b0 1
b1 0
b1000000000100 /
b1000000000000 .
b10000 -
b0 ,
b0 +
0*
0)
b0 (
b0 '
b0 &
b0 %
b10000 $
b0 #
b0 "
0!
$end
#5000
14
#10000
04
07
#15000
b101101001011010010110100101101001011010010110100101101001011010 E
b101101001011010010110100101101001011010010110100101101001011010 S
b101101001011010010110100101101001011010010110100101101001011010 d
b1111111111111111111111111111111111111111111111111111111111111111 &
b1111111111111111111111111111111111111111111111111111111111111111 Q
b1111111111111111111111111111111111111111111111111111111111111111 U
b101101001011010010110100101101001011010010110100101101001011010 "
b101101001011010010110100101101001011010010110100101101001011010 F
b101101001011010010110100101101001011010010110100101101001011010 _
b101101001011010010110100101101001011010010110100101101001011010 b
b1010010110100101101001011010010110100101101001011010010110100101 G
b1010010110100101101001011010010110100101101001011010010110100101 T
b1010010110100101101001011010010110100101101001011010010110100101 Z
b1000000000100 %
b1000000000100 N
b10000 P
b10000 c
b1 #
b1 J
b10 H
b1 I
b1000000010000 $
b1000000010000 M
b1000000000000 O
b101101001011010010110100101101001011010010110100101101001011010 K
b101101001011010010110100101101001011010010110100101101001011010 [
b1010010110100101101001011010010110100101101001011010010110100101 L
b1010010110100101101001011010010110100101101001011010010110100101 V
b10100101101001011010010110100101101001011010010110100101101001010101101001011010010110100101101001011010010110100101101001011010000000000000000000000000000000000000000000000000000100000000000000001000100000100000000000000000000000000000000000000000000000000000000000100000000000000000000000000000000000000000000000000000001000000000100 a
14
#20000
b10000 E
b10000 S
b10000 d
b1010010110100101101001011010010110100101101001011010010110010101 &
b1010010110100101101001011010010110100101101001011010010110010101 Q
b1010010110100101101001011010010110100101101001011010010110010101 U
04
1)
b1 '
b1 8
b1 R
#25000
14
#30000
b1101111010101101101111101110111111011110101011011011111011011111 &
b1101111010101101101111101110111111011110101011011011111011011111 Q
b1101111010101101101111101110111111011110101011011011111011011111 U
b1101111010101101101111101110111111011110101011011011111011101111 "
b1101111010101101101111101110111111011110101011011011111011101111 F
b1101111010101101101111101110111111011110101011011011111011101111 _
b1101111010101101101111101110111111011110101011011011111011101111 b
b1101111010101101101111101110111111011110101011011011111011101111 G
b1101111010101101101111101110111111011110101011011011111011101111 T
b1101111010101101101111101110111111011110101011011011111011101111 Z
04
b1101111010101101101111101110111111011110101011011011111011101111 1
b1101111010101101101111101110111111011110101011011011111011101111 @
b1101111010101101101111101110111111011110101011011011111011101111 W
b1101111010101101101111101110111111011110101011011011111011101111 \
b1 ,
b1 ;
b1 ^
b1 +
b1 :
b1 Y
#35000
14
#40000
04
1*
#45000
b1101111010101101101111101110111111011110101011011011111011101111 &
b1101111010101101101111101110111111011110101011011011111011101111 Q
b1101111010101101101111101110111111011110101011011011111011101111 U
b0 E
b0 S
b0 d
b0 %
b0 N
b0 P
b0 c
b0 #
b0 J
b0 H
b0 I
b10000 $
b10000 M
b0 O
b0 K
b0 [
b0 L
b0 V
b0 a
14
#50000
b1001000110100010101100111100010011010101111001101111011110000 &
b1001000110100010101100111100010011010101111001101111011110000 Q
b1001000110100010101100111100010011010101111001101111011110000 U
b1001000110100010101100111100010011010101111001101111011110000 G
b1001000110100010101100111100010011010101111001101111011110000 T
b1001000110100010101100111100010011010101111001101111011110000 Z
04
b10 +
b10 :
b10 Y
b1001000110100010101100111100010011010101111001101111011110000 (
b1001000110100010101100111100010011010101111001101111011110000 9
b1001000110100010101100111100010011010101111001101111011110000 X
b1001000110100010101100111100010011010101111001101111011110000 ]
0*
#55000
b1001000110100010101100111100010011010101111001101111011100000 &
b1001000110100010101100111100010011010101111001101111011100000 Q
b1001000110100010101100111100010011010101111001101111011100000 U
b10000 E
b10000 S
b10000 d
b1000000000100 %
b1000000000100 N
b10000 P
b10000 c
b1 #
b1 J
b10 H
b1 I
b1000000010000 $
b1000000010000 M
b1000000000000 O
b101101001011010010110100101101001011010010110100101101001011010 K
b101101001011010010110100101101001011010010110100101101001011010 [
b1010010110100101101001011010010110100101101001011010010110100101 L
b1010010110100101101001011010010110100101101001011010010110100101 V
b10100101101001011010010110100101101001011010010110100101101001010101101001011010010110100101101001011010010110100101101001011010000000000000000000000000000000000000000000000000000100000000000000001000100000100000000000000000000000000000000000000000000000000000000000100000000000000000000000000000000000000000000000000000001000000000100 a
14
#60000
b10000 &
b10000 Q
b10000 U
04
b10 '
b10 8
b10 R
#65000
14
#70000
b0 &
b0 Q
b0 U
04
b110 '
b110 8
b110 R
